LICENSE
README.md
ptouch_py/__init__.py
ptouch_py/const.py
ptouch_py/core.py
ptouch_py/domain.py
ptouch_py/registry.py
tapen/__init__.py
tapen/__version__.py
tapen/cli.py
tapen/common/__init__.py
tapen/common/domain.py
tapen/config.py
tapen/const.py
tapen/library/__init__.py
tapen/library/loader.py
tapen/printer/__init__.py
tapen/printer/brother.py
tapen/printer/common.py
tapen/renderer/__init__.py
tapen/renderer/common.py
tapen/renderer/processor.py
tapen/renderer/resources/default.css
tapen/renderer/weasyprint.py
tapen/resources/std-lib/default/manifest.yaml
tapen/utils.py
tapen/validate.py
tapen-0.2.0.dist-info/LICENSE
tapen-0.2.0.dist-info/METADATA
tapen-0.2.0.dist-info/WHEEL
tapen-0.2.0.dist-info/entry_points.txt
tapen-0.2.0.dist-info/RECORD
